gummypy/__init__.py
gummypy/flags.py
gummypy/lib.py
gummypy-1.1.1.dist-info/licenses/LICENSE
gummypy-1.1.1.dist-info/METADATA
gummypy-1.1.1.dist-info/WHEEL
gummypy-1.1.1.dist-info/top_level.txt
gummypy-1.1.1.dist-info/RECORD
