Metadata-Version: 2.4
Name: gummypy
Version: 1.1.1
Summary: A simple library that contains wrapper functions for gum CLI tool
Author-email: sereinne <akbarpersonalmode@gmail.com>
License-Expression: MIT
Project-URL: Homepage, https://github.com/sereinne/gummypy
Project-URL: Repository, https://github.com/sereinne/gummypy
Project-URL: Issues, https://github.com/sereinne/gummypy/issues
Keywords: CLI
Requires-Python: >=3.11
License-File: LICENSE
Dynamic: license-file
